hawk_tui/__init__.py
hawk_tui/db_connectors/__init__.py
hawk_tui/db_connectors/elasticsearch.py
hawk_tui/db_connectors/kafka.py
hawk_tui/db_connectors/mysql.py
hawk_tui/db_connectors/postgresql.py
hawk_tui/db_connectors/redis.py
hawk_tui/main.py
hawk_tui-0.1.0.dist-info/METADATA
hawk_tui-0.1.0.dist-info/WHEEL
hawk_tui-0.1.0.dist-info/entry_points.txt
hawk_tui-0.1.0.dist-info/RECORD
