Metadata-Version: 2.1
Name: hawk-tui
Version: 0.1.0
Summary: Connect to that thang
Home-page: https://github.com/davydany/hawk-tui
License: GPL-3.0-or-later
Keywords: database,tui,connector
Author: David Daniel
Author-email: davydany@gmail.com
Requires-Python: >=3.12.3,<4.0.0
Classifier: License :: OSI Approved :: GNU General Public License v3 or later (GPLv3+)
Classifier: Programming Language :: Python :: 3
Requires-Dist: click (>=8.1.3,<9.0.0)
Requires-Dist: elasticsearch (>=8.6.2,<9.0.0)
Requires-Dist: kafka-python (>=2.0.2,<3.0.0)
Requires-Dist: mysql-connector-python (>=8.0.32,<9.0.0)
Requires-Dist: psycopg2-binary (>=2.9.5,<3.0.0)
Requires-Dist: redis (>=4.5.1,<5.0.0)
Requires-Dist: textual (>=0.27.0,<0.28.0)
Project-URL: Repository, https://github.com/davydany/hawk-tui
